odoo/addons/export_async_schedule/README.rst
odoo/addons/export_async_schedule/__init__.py
odoo/addons/export_async_schedule/__manifest__.py
odoo/addons/export_async_schedule/data/ir_cron.xml
odoo/addons/export_async_schedule/i18n/export_async_schedule.pot
odoo/addons/export_async_schedule/i18n/fr.po
odoo/addons/export_async_schedule/models/__init__.py
odoo/addons/export_async_schedule/models/export_async_schedule.py
odoo/addons/export_async_schedule/readme/CONFIGURE.rst
odoo/addons/export_async_schedule/readme/CONTRIBUTORS.rst
odoo/addons/export_async_schedule/readme/DESCRIPTION.rst
odoo/addons/export_async_schedule/readme/ROADMAP.rst
odoo/addons/export_async_schedule/readme/USAGE.rst
odoo/addons/export_async_schedule/security/ir.model.access.csv
odoo/addons/export_async_schedule/static/description/icon.png
odoo/addons/export_async_schedule/static/description/index.html
odoo/addons/export_async_schedule/tests/__init__.py
odoo/addons/export_async_schedule/tests/test_export_async_schedule.py
odoo/addons/export_async_schedule/views/export_async_schedule_views.xml
odoo12_addon_export_async_schedule-12.0.1.0.0.99.dev10.dist-info/METADATA
odoo12_addon_export_async_schedule-12.0.1.0.0.99.dev10.dist-info/WHEEL
odoo12_addon_export_async_schedule-12.0.1.0.0.99.dev10.dist-info/top_level.txt
odoo12_addon_export_async_schedule-12.0.1.0.0.99.dev10.dist-info/RECORD
